{
  "sl_streaks": {
    "SZSE:000725": 0,
    "NYSE:LLY": 0,
    "BYBIT:HYPEUSDC.P": 0,
    "NYSE:CAT": 0,
    "NASDAQ:AAPL": 0,
    "COINBASE:GOLDUSDC.P": 0,
    "HYPERLIQUID:XLMUSDC.P": 0,
    "OANDA:EURUSD": 0,
    "OANDA:USDJPY": 0,
    "OANDA:AUDJPY": 0,
    "OANDA:CADJPY": 0,
    "HYPERLIQUID:XRPUSDC.P": 0,
    "HYPERLIQUID:SOLUSDC.P": 0,
    "HYPERLIQUID:INJUSDC.P": 0,
    "HYPERLIQUID:ETHUSDC.P": 0,
    "HYPERLIQUID:LINKUSDC.P": 0,
    "HYPERLIQUID:BTCUSDC.P": 0,
    "HYPERLIQUID:SUIUSDC.P": 0
  },
  "symbol_state": {
    "PIONEX:BRENTOILUSDT.P": {
      "last_pull": "2026-07-09T17:05:49"
    },
    "BLOFIN:WTIOILUSDT.P": {
      "last_pull": "2026-07-09T17:01:19",
      "last_signal": "2026-07-07T16:03:58",
      "last_signal_val": 1
    },
    "OANDA:EURUSD": {
      "last_pull": "2026-07-15T13:08:37",
      "last_signal": "2026-07-02T08:07:34",
      "last_signal_val": 1
    },
    "OANDA:GBPUSD": {
      "last_pull": "2026-07-15T13:08:55",
      "last_signal": "2026-07-15T13:08:55",
      "last_signal_val": 1
    },
    "BYBIT:ETHUSDC.P": {
      "last_pull": "2026-07-09T17:01:55"
    },
    "BYBIT:LINKUSDC.P": {
      "last_pull": "2026-07-09T17:02:49"
    },
    "BYBIT:INJUSDC.P": {
      "last_pull": "2026-07-09T17:02:31",
      "last_signal": "2026-07-09T10:04:57",
      "last_signal_val": 1
    },
    "BYBIT:XRPUSDC.P": {
      "last_pull": "2026-07-09T17:04:01",
      "last_signal": "2026-07-02T07:54:48",
      "last_signal_val": 1
    },
    "COINBASE:RENDERUSD": {
      "last_pull": "2026-07-09T17:04:55"
    },
    "BYBIT:SUIUSDC.P": {
      "last_pull": "2026-07-09T17:03:43",
      "last_signal": "2026-06-30T10:37:44",
      "last_signal_val": 1
    },
    "BYBIT:BTCUSDC.P": {
      "last_pull": "2026-07-09T17:01:37"
    },
    "BYBIT:HYPEUSDC.P": {
      "last_pull": "2026-07-09T17:02:13"
    },
    "BYBIT:SOLUSDC.P": {
      "last_pull": "2026-07-09T17:03:25"
    },
    "BYBIT:ONDOUSDC.P": {
      "last_pull": "2026-07-09T17:03:07"
    },
    "OANDA:USDJPY": {
      "last_pull": "2026-07-15T13:09:31",
      "last_signal": "2026-07-13T13:09:32",
      "last_signal_val": 1
    },
    "OANDA:AUDUSD": {
      "last_pull": "2026-07-15T13:08:19",
      "last_signal": "2026-07-02T08:07:16",
      "last_signal_val": 1
    },
    "OANDA:NZDUSD": {
      "last_pull": "2026-07-15T13:09:13",
      "last_signal": "2026-06-30T08:13:19",
      "last_signal_val": 1
    },
    "COINBASE:GOLDUSDC.P": {
      "last_pull": "2026-07-09T17:04:19",
      "last_signal": "2026-07-02T07:55:08",
      "last_signal_val": 1
    },
    "COINBASE:SILVERUSDC.P": {
      "last_pull": "2026-07-09T17:05:13"
    },
    "SZSE:000725": {
      "last_pull": "2026-07-14T21:14:10"
    },
    "SZSE:002415": {
      "last_pull": "2026-07-14T21:14:46"
    },
    "NYSE:LLY": {
      "last_pull": "2026-07-15T09:15:50"
    },
    "NYSE:DELL": {
      "last_pull": "2026-07-15T09:13:26"
    },
    "NYSE:CAT": {
      "last_pull": "2026-07-15T09:13:08"
    },
    "NYSE:KO": {
      "last_pull": "2026-07-15T09:15:32"
    },
    "NYSE:GS": {
      "last_pull": "2026-07-15T09:14:20",
      "last_signal": "2026-07-15T09:14:20",
      "last_signal_val": 1
    },
    "NYSE:MS": {
      "last_pull": "2026-07-15T09:16:44"
    },
    "NYSE:HPE": {
      "last_pull": "2026-07-01T12:56:39"
    },
    "NASDAQ:CSCO": {
      "last_pull": "2026-07-15T09:09:32",
      "last_signal": "2026-07-09T10:12:09",
      "last_signal_val": 1
    },
    "NASDAQ:AAPL": {
      "last_pull": "2026-07-15T09:08:19",
      "last_signal": "2026-07-01T12:57:15",
      "last_signal_val": 1
    },
    "NASDAQ:AMAT": {
      "last_pull": "2026-07-15T09:08:37"
    },
    "NASDAQ:AMD": {
      "last_pull": "2026-07-15T09:08:55"
    },
    "NASDAQ:AMGN": {
      "last_pull": "2026-07-15T09:09:14"
    },
    "NASDAQ:FTNT": {
      "last_pull": "2026-07-15T09:09:50"
    },
    "NASDAQ:KLAC": {
      "last_pull": "2026-07-15T09:10:08"
    },
    "NASDAQ:MNST": {
      "last_pull": "2026-07-15T09:10:26"
    },
    "NASDAQ:PANW": {
      "last_pull": "2026-07-15T09:10:44"
    },
    "NASDAQ:PYPL": {
      "last_pull": "2026-07-15T09:11:02"
    },
    "NASDAQ:REGN": {
      "last_pull": "2026-07-15T09:11:20"
    },
    "NASDAQ:SBUX": {
      "last_pull": "2026-07-15T09:11:38"
    },
    "NASDAQ:VRTX": {
      "last_pull": "2026-07-15T09:11:56"
    },
    "NYSE:ABT": {
      "last_pull": "2026-07-15T09:12:14"
    },
    "NYSE:AXP": {
      "last_pull": "2026-07-15T09:12:32"
    },
    "NYSE:BAC": {
      "last_pull": "2026-07-15T09:12:50"
    },
    "NYSE:DHR": {
      "last_pull": "2026-07-15T09:13:44"
    },
    "NYSE:GE": {
      "last_pull": "2026-07-15T09:14:02"
    },
    "NYSE:HD": {
      "last_pull": "2026-07-15T09:14:38"
    },
    "NYSE:JNJ": {
      "last_pull": "2026-07-15T09:14:56"
    },
    "NYSE:JPM": {
      "last_pull": "2026-07-15T09:15:14"
    },
    "NYSE:MA": {
      "last_pull": "2026-07-15T09:16:08"
    },
    "NYSE:MRK": {
      "last_pull": "2026-07-15T09:16:26"
    },
    "NYSE:RTX": {
      "last_pull": "2026-07-15T09:17:02"
    },
    "NYSE:TMO": {
      "last_pull": "2026-07-15T09:17:20"
    },
    "NYSE:UNH": {
      "last_pull": "2026-07-15T09:17:38"
    },
    "NYSE:V": {
      "last_pull": "2026-07-15T09:17:56"
    },
    "NYSE:WFC": {
      "last_pull": "2026-07-15T09:18:14"
    },
    "SSE:600028": {
      "last_pull": "2026-07-14T21:09:40",
      "last_signal": "2026-07-05T23:34:36",
      "last_signal_val": 1
    },
    "SSE:600030": {
      "last_pull": "2026-07-14T21:09:58"
    },
    "SSE:600111": {
      "last_pull": "2026-07-14T21:10:16"
    },
    "SSE:600346": {
      "last_pull": "2026-07-14T21:11:28"
    },
    "SSE:600460": {
      "last_pull": "2026-07-14T21:11:46"
    },
    "SSE:601211": {
      "last_pull": "2026-07-14T21:12:04"
    },
    "SSE:601229": {
      "last_pull": "2026-07-14T21:12:22",
      "last_signal": "2026-07-13T21:12:20",
      "last_signal_val": 1
    },
    "SSE:601628": {
      "last_pull": "2026-07-14T21:12:40",
      "last_signal": "2026-07-14T21:12:40",
      "last_signal_val": 1
    },
    "SSE:601688": {
      "last_pull": "2026-07-14T21:12:58"
    },
    "SZSE:000538": {
      "last_pull": "2026-07-14T21:13:34",
      "last_signal": "2026-07-02T22:13:05",
      "last_signal_val": 1
    },
    "SZSE:002493": {
      "last_pull": "2026-07-14T21:15:04",
      "last_signal": "2026-07-05T23:49:20",
      "last_signal_val": 1
    },
    "COINBASE:HBARUSDC.P": {
      "last_pull": "2026-07-09T17:04:37"
    },
    "COINBASE:XLMUSDC.P": {
      "last_pull": "2026-07-09T17:05:31"
    },
    "SSE:600196": {
      "last_pull": "2026-07-14T21:10:34",
      "last_signal": "2026-07-14T21:10:34",
      "last_signal_val": 1
    },
    "SSE:600276": {
      "last_pull": "2026-07-14T21:10:52"
    },
    "SSE:600309": {
      "last_pull": "2026-07-14T21:11:10"
    },
    "SZSE:000651": {
      "last_pull": "2026-07-14T21:13:52"
    },
    "SZSE:002236": {
      "last_pull": "2026-07-14T21:14:28"
    },
    "SZSE:002714": {
      "last_pull": "2026-07-14T21:15:22"
    },
    "SZSE:300015": {
      "last_pull": "2026-07-14T21:15:40"
    },
    "SZSE:300059": {
      "last_pull": "2026-07-14T21:15:58"
    },
    "HYPERLIQUID:BTCUSDC.P": {
      "last_pull": "2026-07-15T13:02:02"
    },
    "HYPERLIQUID:ETHUSDC.P": {
      "last_pull": "2026-07-15T13:03:04",
      "last_signal": "2026-07-14T09:03:05",
      "last_signal_val": 1
    },
    "HYPERLIQUID:HBARUSDC.P": {
      "last_pull": "2026-07-15T13:04:06"
    },
    "HYPERLIQUID:HYPEUSDC.P": {
      "last_pull": "2026-07-15T13:04:24",
      "last_signal": "2026-07-14T21:04:25",
      "last_signal_val": 1
    },
    "HYPERLIQUID:INJUSDC.P": {
      "last_pull": "2026-07-15T13:04:42",
      "last_signal": "2026-07-14T01:04:42",
      "last_signal_val": 1
    },
    "HYPERLIQUID:LINKUSDC.P": {
      "last_pull": "2026-07-15T13:05:00"
    },
    "HYPERLIQUID:NEARUSDC.P": {
      "last_pull": "2026-07-15T13:05:18",
      "last_signal": "2026-07-14T01:05:18",
      "last_signal_val": 1
    },
    "HYPERLIQUID:ONDOUSDC.P": {
      "last_pull": "2026-07-15T13:05:36",
      "last_signal": "2026-07-15T09:05:47",
      "last_signal_val": 1
    },
    "HYPERLIQUID:RENDERUSDC.P": {
      "last_pull": "2026-07-15T13:05:54",
      "last_signal": "2026-07-15T09:06:05",
      "last_signal_val": 1
    },
    "HYPERLIQUID:SOLUSDC.P": {
      "last_pull": "2026-07-15T13:06:56",
      "last_signal": "2026-07-15T01:06:56",
      "last_signal_val": 1
    },
    "HYPERLIQUID:SUIUSDC.P": {
      "last_pull": "2026-07-15T13:07:25",
      "last_signal": "2026-07-14T21:07:15",
      "last_signal_val": 1
    },
    "HYPERLIQUID:XLMUSDC.P": {
      "last_pull": "2026-07-15T13:07:43",
      "last_signal": "2026-07-15T09:07:43",
      "last_signal_val": 1
    },
    "HYPERLIQUID:XRPUSDC.P": {
      "last_pull": "2026-07-15T13:08:01",
      "last_signal": "2026-07-14T09:07:51",
      "last_signal_val": 1
    },
    "SZSE:000333": {
      "last_pull": "2026-07-14T21:13:16"
    }
  },
  "open_trades": {
    "OANDA:AUDUSD": {
      "pair": "OANDA:AUDUSD",
      "direction": "long",
      "entry": 0.68951,
      "tp": 0.70604,
      "sl": 0.69115,
      "atr": 0,
      "size": 200000,
      "notional": 0,
      "features": {},
      "bar_time": null,
      "open_time": "2026-07-12T18:53:29",
      "closed": false,
      "close_price": null,
      "close_reason": null,
      "result": null,
      "protected_sl": null,
      "runner_active": false,
      "runner_regime": null,
      "bars_since_close": 0,
      "price_triggers": [],
      "watcher_tp": null,
      "watcher_sl": null,
      "manual_tp": null,
      "manual_sl": null,
      "sl_tp_source": null,
      "software_watch_units": 0.0
    },
    "OANDA:NZDUSD": {
      "pair": "OANDA:NZDUSD",
      "direction": "long",
      "entry": 0.57893,
      "tp": 0.5921,
      "sl": 0.57363,
      "atr": 0,
      "size": 20000,
      "notional": 0,
      "features": {},
      "bar_time": null,
      "open_time": "2026-07-13T09:33:39",
      "closed": false,
      "close_price": null,
      "close_reason": null,
      "result": null,
      "protected_sl": null,
      "runner_active": false,
      "runner_regime": null,
      "bars_since_close": 0,
      "price_triggers": [],
      "watcher_tp": null,
      "watcher_sl": null,
      "manual_tp": null,
      "manual_sl": null,
      "sl_tp_source": null,
      "software_watch_units": 0.0
    },
    "OANDA:USDCHF": {
      "pair": "OANDA:USDCHF",
      "direction": "long",
      "entry": 0.81084,
      "tp": null,
      "sl": null,
      "atr": 0,
      "size": 1.0,
      "notional": 0,
      "features": {},
      "bar_time": null,
      "open_time": "2026-07-13T06:51:08",
      "closed": true,
      "close_price": null,
      "close_reason": "synced_from_oanda",
      "result": null,
      "protected_sl": null,
      "runner_active": false,
      "runner_regime": null,
      "bars_since_close": 0,
      "price_triggers": [],
      "watcher_tp": null,
      "watcher_sl": null,
      "manual_tp": null,
      "manual_sl": null,
      "sl_tp_source": null,
      "software_watch_units": 0.0
    },
    "OANDA:EURAUD": {
      "pair": "OANDA:EURAUD",
      "direction": "long",
      "entry": 1.64514,
      "tp": null,
      "sl": null,
      "atr": 0,
      "size": 1.0,
      "notional": 0,
      "features": {},
      "bar_time": null,
      "open_time": "2026-07-12T22:48:43",
      "closed": true,
      "close_price": null,
      "close_reason": "synced_from_oanda",
      "result": null,
      "protected_sl": null,
      "runner_active": false,
      "runner_regime": null,
      "bars_since_close": 0,
      "price_triggers": [],
      "watcher_tp": null,
      "watcher_sl": null,
      "manual_tp": null,
      "manual_sl": null,
      "sl_tp_source": null,
      "software_watch_units": 0.0
    },
    "OANDA:NZDJPY": {
      "pair": "OANDA:NZDJPY",
      "direction": "long",
      "entry": 93.456,
      "tp": null,
      "sl": null,
      "atr": 0,
      "size": 1.0,
      "notional": 0,
      "features": {},
      "bar_time": null,
      "open_time": "2026-07-12T18:57:49",
      "closed": true,
      "close_price": null,
      "close_reason": "synced_from_oanda",
      "result": null,
      "protected_sl": null,
      "runner_active": false,
      "runner_regime": null,
      "bars_since_close": 0,
      "price_triggers": [],
      "watcher_tp": null,
      "watcher_sl": null,
      "manual_tp": null,
      "manual_sl": null,
      "sl_tp_source": null,
      "software_watch_units": 0.0
    },
    "BATS:FCX": {
      "pair": "BATS:FCX",
      "direction": "long",
      "entry": 62.28,
      "tp": null,
      "sl": null,
      "atr": 0,
      "size": 1.0,
      "notional": 0,
      "features": {},
      "bar_time": null,
      "open_time": "2026-07-10T07:33:59",
      "closed": false,
      "close_price": null,
      "close_reason": null,
      "result": null,
      "protected_sl": null,
      "runner_active": false,
      "runner_regime": null,
      "bars_since_close": 0,
      "price_triggers": [],
      "watcher_tp": null,
      "watcher_sl": null,
      "manual_tp": null,
      "manual_sl": null,
      "sl_tp_source": null,
      "software_watch_units": 0.0
    },
    "OANDA:AUDNZD": {
      "pair": "OANDA:AUDNZD",
      "direction": "long",
      "entry": 1.20046,
      "tp": 1.21603,
      "sl": 1.19338,
      "atr": 0,
      "size": 10000,
      "notional": 0,
      "features": {},
      "bar_time": null,
      "open_time": "2026-07-12T18:40:44",
      "closed": false,
      "close_price": null,
      "close_reason": null,
      "result": null,
      "protected_sl": null,
      "runner_active": false,
      "runner_regime": null,
      "bars_since_close": 0,
      "price_triggers": [],
      "watcher_tp": null,
      "watcher_sl": null,
      "manual_tp": null,
      "manual_sl": null,
      "sl_tp_source": null,
      "software_watch_units": 0.0
    },
    "OANDA:GBPJPY": {
      "pair": "OANDA:GBPJPY",
      "direction": "long",
      "entry": 217.067,
      "tp": null,
      "sl": null,
      "atr": 0,
      "size": 1.0,
      "notional": 0,
      "features": {},
      "bar_time": null,
      "open_time": "2026-07-12T22:54:04",
      "closed": true,
      "close_price": null,
      "close_reason": "synced_from_oanda",
      "result": null,
      "protected_sl": null,
      "runner_active": false,
      "runner_regime": null,
      "bars_since_close": 0,
      "price_triggers": [],
      "watcher_tp": null,
      "watcher_sl": null,
      "manual_tp": null,
      "manual_sl": null,
      "sl_tp_source": null,
      "software_watch_units": 0.0
    },
    "BATS:AMAT": {
      "pair": "BATS:AMAT",
      "direction": "long",
      "entry": 614.789947,
      "tp": null,
      "sl": null,
      "atr": 0.0,
      "size": 16.265701881,
      "notional": 0,
      "features": {},
      "bar_time": null,
      "open_time": "2026-07-10T08:39:47",
      "closed": false,
      "close_price": null,
      "close_reason": null,
      "result": null,
      "protected_sl": null,
      "runner_active": false,
      "runner_regime": null,
      "bars_since_close": 0,
      "price_triggers": [],
      "watcher_tp": null,
      "watcher_sl": null,
      "manual_tp": null,
      "manual_sl": null,
      "sl_tp_source": null,
      "software_watch_units": 0.0
    },
    "BATS:AXP": {
      "pair": "BATS:AXP",
      "direction": "long",
      "entry": 353.968299,
      "tp": null,
      "sl": null,
      "atr": 0.0,
      "size": 28.251089232,
      "notional": 0,
      "features": {},
      "bar_time": null,
      "open_time": "2026-07-10T08:39:47",
      "closed": false,
      "close_price": null,
      "close_reason": null,
      "result": null,
      "protected_sl": null,
      "runner_active": false,
      "runner_regime": null,
      "bars_since_close": 0,
      "price_triggers": [],
      "watcher_tp": null,
      "watcher_sl": null,
      "manual_tp": null,
      "manual_sl": null,
      "sl_tp_source": null,
      "software_watch_units": 0.0
    },
    "BATS:GE": {
      "pair": "BATS:GE",
      "direction": "long",
      "entry": 377.96,
      "tp": null,
      "sl": null,
      "atr": 0.0,
      "size": 26.457799767,
      "notional": 0,
      "features": {},
      "bar_time": null,
      "open_time": "2026-07-10T08:39:47",
      "closed": false,
      "close_price": null,
      "close_reason": null,
      "result": null,
      "protected_sl": null,
      "runner_active": false,
      "runner_regime": null,
      "bars_since_close": 0,
      "price_triggers": [],
      "watcher_tp": null,
      "watcher_sl": null,
      "manual_tp": null,
      "manual_sl": null,
      "sl_tp_source": null,
      "software_watch_units": 0.0
    },
    "BATS:KLAC": {
      "pair": "BATS:KLAC",
      "direction": "long",
      "entry": 244.115638,
      "tp": null,
      "sl": null,
      "atr": 0.0,
      "size": 40.964151559,
      "notional": 0,
      "features": {},
      "bar_time": null,
      "open_time": "2026-07-10T08:39:47",
      "closed": false,
      "close_price": null,
      "close_reason": null,
      "result": null,
      "protected_sl": null,
      "runner_active": false,
      "runner_regime": null,
      "bars_since_close": 0,
      "price_triggers": [],
      "watcher_tp": null,
      "watcher_sl": null,
      "manual_tp": null,
      "manual_sl": null,
      "sl_tp_source": null,
      "software_watch_units": 0.0
    },
    "BATS:LLY": {
      "pair": "BATS:LLY",
      "direction": "short",
      "entry": 1143.33,
      "tp": null,
      "sl": null,
      "atr": 0,
      "size": 1.0,
      "notional": 0,
      "features": {},
      "bar_time": null,
      "open_time": "2026-07-13T06:51:27",
      "closed": false,
      "close_price": null,
      "close_reason": null,
      "result": null,
      "protected_sl": null,
      "runner_active": false,
      "runner_regime": null,
      "bars_since_close": 0,
      "price_triggers": [],
      "watcher_tp": null,
      "watcher_sl": null,
      "manual_tp": null,
      "manual_sl": null,
      "sl_tp_source": null,
      "software_watch_units": 0.0
    },
    "BATS:PANW": {
      "pair": "BATS:PANW",
      "direction": "long",
      "entry": 349.250239,
      "tp": null,
      "sl": null,
      "atr": 0.0,
      "size": 28.63273627,
      "notional": 0,
      "features": {},
      "bar_time": null,
      "open_time": "2026-07-10T08:39:47",
      "closed": false,
      "close_price": null,
      "close_reason": null,
      "result": null,
      "protected_sl": null,
      "runner_active": false,
      "runner_regime": null,
      "bars_since_close": 0,
      "price_triggers": [],
      "watcher_tp": null,
      "watcher_sl": null,
      "manual_tp": null,
      "manual_sl": null,
      "sl_tp_source": null,
      "software_watch_units": 0.0
    },
    "BATS:PYPL": {
      "pair": "BATS:PYPL",
      "direction": "long",
      "entry": 44.08,
      "tp": null,
      "sl": null,
      "atr": 0.0,
      "size": 340.290154264,
      "notional": 0,
      "features": {},
      "bar_time": null,
      "open_time": "2026-07-10T08:39:47",
      "closed": false,
      "close_price": null,
      "close_reason": null,
      "result": null,
      "protected_sl": null,
      "runner_active": false,
      "runner_regime": null,
      "bars_since_close": 0,
      "price_triggers": [],
      "watcher_tp": null,
      "watcher_sl": null,
      "manual_tp": null,
      "manual_sl": null,
      "sl_tp_source": null,
      "software_watch_units": 0.0
    },
    "BATS:TMO": {
      "pair": "BATS:TMO",
      "direction": "long",
      "entry": 512.24,
      "tp": null,
      "sl": null,
      "atr": 0.0,
      "size": 29.283129002,
      "notional": 0,
      "features": {},
      "bar_time": null,
      "open_time": "2026-07-10T08:39:47",
      "closed": false,
      "close_price": null,
      "close_reason": null,
      "result": null,
      "protected_sl": null,
      "runner_active": false,
      "runner_regime": null,
      "bars_since_close": 0,
      "price_triggers": [],
      "watcher_tp": null,
      "watcher_sl": null,
      "manual_tp": null,
      "manual_sl": null,
      "sl_tp_source": null,
      "software_watch_units": 0.0
    },
    "BATS:VRTX": {
      "pair": "BATS:VRTX",
      "direction": "long",
      "entry": 525.5,
      "tp": null,
      "sl": null,
      "atr": 0.0,
      "size": 19.029476688,
      "notional": 0,
      "features": {},
      "bar_time": null,
      "open_time": "2026-07-10T08:39:47",
      "closed": false,
      "close_price": null,
      "close_reason": null,
      "result": null,
      "protected_sl": null,
      "runner_active": false,
      "runner_regime": null,
      "bars_since_close": 0,
      "price_triggers": [],
      "watcher_tp": null,
      "watcher_sl": null,
      "manual_tp": null,
      "manual_sl": null,
      "sl_tp_source": null,
      "software_watch_units": 0.0
    },
    "HYPERLIQUID:ONDOUSDC.P": {
      "pair": "HYPERLIQUID:ONDOUSDC.P",
      "direction": "long",
      "entry": 0.332475,
      "tp": 0.3886,
      "sl": 0.3126,
      "atr": 0,
      "size": 1.0,
      "notional": 0,
      "features": {},
      "bar_time": null,
      "open_time": "2026-07-12T18:59:17",
      "closed": false,
      "close_price": null,
      "close_reason": null,
      "result": null,
      "protected_sl": null,
      "runner_active": false,
      "runner_regime": null,
      "bars_since_close": 0,
      "price_triggers": [],
      "watcher_tp": null,
      "watcher_sl": null,
      "manual_tp": null,
      "manual_sl": null,
      "sl_tp_source": null,
      "software_watch_units": 0.0
    },
    "HYPERLIQUID:HYPEUSDC.P": {
      "pair": "HYPERLIQUID:HYPEUSDC.P",
      "direction": "long",
      "entry": 67.2928,
      "tp": 77.97,
      "sl": 63.27,
      "atr": 0,
      "size": 5000,
      "notional": 0,
      "features": {},
      "bar_time": null,
      "open_time": "2026-07-15T16:19:02",
      "closed": false,
      "close_price": null,
      "close_reason": null,
      "result": null,
      "protected_sl": null,
      "runner_active": false,
      "runner_regime": null,
      "bars_since_close": 0,
      "price_triggers": [],
      "watcher_tp": 77.97,
      "watcher_sl": 63.27,
      "manual_tp": null,
      "manual_sl": null,
      "sl_tp_source": null,
      "software_watch_units": 0.0
    },
    "OANDA:USDCNH": {
      "pair": "OANDA:USDCNH",
      "direction": "short",
      "entry": 6.77032,
      "tp": 6.7671,
      "sl": 6.8079,
      "atr": 0,
      "size": 20000,
      "notional": 0,
      "features": {},
      "bar_time": null,
      "open_time": "2026-07-13T02:55:20",
      "closed": false,
      "close_price": null,
      "close_reason": null,
      "result": null,
      "protected_sl": null,
      "runner_active": false,
      "runner_regime": null,
      "bars_since_close": 0,
      "price_triggers": [],
      "watcher_tp": null,
      "watcher_sl": null,
      "manual_tp": null,
      "manual_sl": null,
      "sl_tp_source": null,
      "software_watch_units": 0.0
    },
    "TVC:GB30Y": {
      "pair": "TVC:GB30Y",
      "direction": "short",
      "entry": 5.646,
      "tp": null,
      "sl": null,
      "atr": 0,
      "size": 1.0,
      "notional": 0,
      "features": {},
      "bar_time": null,
      "open_time": "2026-07-13T00:00:21",
      "closed": false,
      "close_price": null,
      "close_reason": null,
      "result": null,
      "protected_sl": null,
      "runner_active": false,
      "runner_regime": null,
      "bars_since_close": 0,
      "price_triggers": [],
      "watcher_tp": null,
      "watcher_sl": null,
      "manual_tp": null,
      "manual_sl": null,
      "sl_tp_source": null,
      "software_watch_units": 0.0
    },
    "TVC:GB10Y": {
      "pair": "TVC:GB10Y",
      "direction": "short",
      "entry": 4.949,
      "tp": null,
      "sl": null,
      "atr": 0,
      "size": 1.0,
      "notional": 0,
      "features": {},
      "bar_time": null,
      "open_time": "2026-07-13T00:01:33",
      "closed": false,
      "close_price": null,
      "close_reason": null,
      "result": null,
      "protected_sl": null,
      "runner_active": false,
      "runner_regime": null,
      "bars_since_close": 0,
      "price_triggers": [],
      "watcher_tp": null,
      "watcher_sl": null,
      "manual_tp": null,
      "manual_sl": null,
      "sl_tp_source": null,
      "software_watch_units": 0.0
    },
    "OANDA:EURGBP": {
      "pair": "OANDA:EURGBP",
      "direction": "long",
      "entry": 0.85422,
      "tp": 0.85374,
      "sl": 0.84179,
      "atr": 0,
      "size": 20000,
      "notional": 0,
      "features": {},
      "bar_time": null,
      "open_time": "2026-07-13T00:34:08",
      "closed": false,
      "close_price": null,
      "close_reason": null,
      "result": null,
      "protected_sl": null,
      "runner_active": false,
      "runner_regime": null,
      "bars_since_close": 0,
      "price_triggers": [],
      "watcher_tp": null,
      "watcher_sl": null,
      "manual_tp": null,
      "manual_sl": null,
      "sl_tp_source": null,
      "software_watch_units": 0.0
    },
    "HYPERLIQUID:NEARUSDC.P": {
      "pair": "HYPERLIQUID:NEARUSDC.P",
      "direction": "long",
      "entry": 1.9228,
      "tp": 2.3935,
      "sl": 1.8416,
      "atr": 0,
      "size": 1.0,
      "notional": 0,
      "features": {},
      "bar_time": null,
      "open_time": "2026-07-13T07:16:51",
      "closed": false,
      "close_price": null,
      "close_reason": null,
      "result": null,
      "protected_sl": null,
      "runner_active": false,
      "runner_regime": null,
      "bars_since_close": 0,
      "price_triggers": [
        {
          "condition": "price_gte",
          "price": 2.0924,
          "action": "move_sl",
          "value": 1.9921,
          "note": "25% \u2192 BE"
        },
        {
          "condition": "price_gte",
          "price": 2.1928,
          "action": "move_sl",
          "value": 2.0924,
          "note": "50% \u2192 25% level"
        },
        {
          "condition": "price_gte",
          "price": 2.2931,
          "action": "move_sl",
          "value": 2.1928,
          "note": "75% \u2192 50% level"
        }
      ],
      "watcher_tp": null,
      "watcher_sl": null,
      "manual_tp": 2.3935,
      "manual_sl": 1.8416,
      "sl_tp_source": null,
      "software_watch_units": 0.0
    },
    "HYPERLIQUID:HBARUSDC.P": {
      "pair": "HYPERLIQUID:HBARUSDC.P",
      "direction": "long",
      "entry": 0.067496,
      "tp": null,
      "sl": null,
      "atr": 0,
      "size": 1.0,
      "notional": 5000,
      "features": {},
      "bar_time": null,
      "open_time": "2026-07-13T09:31:44",
      "closed": false,
      "close_price": null,
      "close_reason": null,
      "result": null,
      "protected_sl": null,
      "runner_active": false,
      "runner_regime": null,
      "bars_since_close": 0,
      "price_triggers": [],
      "watcher_tp": null,
      "watcher_sl": null,
      "manual_tp": null,
      "manual_sl": null,
      "sl_tp_source": null,
      "software_watch_units": 0.0
    },
    "OANDA:GBPAUD": {
      "pair": "OANDA:GBPAUD",
      "direction": "short",
      "entry": 1.92482,
      "tp": 1.91041,
      "sl": 1.94605,
      "atr": 0,
      "size": 10000,
      "notional": 0,
      "features": {},
      "bar_time": null,
      "open_time": "2026-07-13T04:25:39",
      "closed": false,
      "close_price": null,
      "close_reason": null,
      "result": null,
      "protected_sl": null,
      "runner_active": false,
      "runner_regime": null,
      "bars_since_close": 0,
      "price_triggers": [],
      "watcher_tp": null,
      "watcher_sl": null,
      "manual_tp": null,
      "manual_sl": null,
      "sl_tp_source": null,
      "software_watch_units": 0.0
    },
    "BATS:MU": {
      "pair": "BATS:MU",
      "direction": "long",
      "entry": 987.74,
      "tp": null,
      "sl": null,
      "atr": 0,
      "size": 1.0,
      "notional": 0,
      "features": {},
      "bar_time": null,
      "open_time": "2026-07-13T06:30:10",
      "closed": false,
      "close_price": null,
      "close_reason": null,
      "result": null,
      "protected_sl": null,
      "runner_active": false,
      "runner_regime": null,
      "bars_since_close": 0,
      "price_triggers": [],
      "watcher_tp": null,
      "watcher_sl": null,
      "manual_tp": null,
      "manual_sl": null,
      "sl_tp_source": null,
      "software_watch_units": 0.0
    },
    "BATS:VZ": {
      "pair": "BATS:VZ",
      "direction": "long",
      "entry": 42.49,
      "tp": null,
      "sl": null,
      "atr": 0,
      "size": 1.0,
      "notional": 0,
      "features": {},
      "bar_time": null,
      "open_time": "2026-07-13T06:30:23",
      "closed": false,
      "close_price": null,
      "close_reason": null,
      "result": null,
      "protected_sl": null,
      "runner_active": false,
      "runner_regime": null,
      "bars_since_close": 0,
      "price_triggers": [],
      "watcher_tp": null,
      "watcher_sl": null,
      "manual_tp": null,
      "manual_sl": null,
      "sl_tp_source": null,
      "software_watch_units": 0.0
    },
    "BATS:QCOM": {
      "pair": "BATS:QCOM",
      "direction": "short",
      "entry": 184.87,
      "tp": null,
      "sl": null,
      "atr": 0,
      "size": 1.0,
      "notional": 0,
      "features": {},
      "bar_time": null,
      "open_time": "2026-07-13T06:30:24",
      "closed": false,
      "close_price": null,
      "close_reason": null,
      "result": null,
      "protected_sl": null,
      "runner_active": false,
      "runner_regime": null,
      "bars_since_close": 0,
      "price_triggers": [],
      "watcher_tp": null,
      "watcher_sl": null,
      "manual_tp": null,
      "manual_sl": null,
      "sl_tp_source": null,
      "software_watch_units": 0.0
    },
    "BATS:NFLX": {
      "pair": "BATS:NFLX",
      "direction": "short",
      "entry": 72.6,
      "tp": null,
      "sl": null,
      "atr": 0,
      "size": 1.0,
      "notional": 0,
      "features": {},
      "bar_time": null,
      "open_time": "2026-07-13T06:30:30",
      "closed": false,
      "close_price": null,
      "close_reason": null,
      "result": null,
      "protected_sl": null,
      "runner_active": false,
      "runner_regime": null,
      "bars_since_close": 0,
      "price_triggers": [],
      "watcher_tp": null,
      "watcher_sl": null,
      "manual_tp": null,
      "manual_sl": null,
      "sl_tp_source": null,
      "software_watch_units": 0.0
    },
    "BATS:RTX": {
      "pair": "BATS:RTX",
      "direction": "short",
      "entry": 193.93,
      "tp": null,
      "sl": null,
      "atr": 0,
      "size": 1.0,
      "notional": 0,
      "features": {},
      "bar_time": null,
      "open_time": "2026-07-13T06:30:30",
      "closed": false,
      "close_price": null,
      "close_reason": null,
      "result": null,
      "protected_sl": null,
      "runner_active": false,
      "runner_regime": null,
      "bars_since_close": 0,
      "price_triggers": [],
      "watcher_tp": null,
      "watcher_sl": null,
      "manual_tp": null,
      "manual_sl": null,
      "sl_tp_source": null,
      "software_watch_units": 0.0
    },
    "BATS:DELL": {
      "pair": "BATS:DELL",
      "direction": "long",
      "entry": 441.8,
      "tp": null,
      "sl": null,
      "atr": 0,
      "size": 1.0,
      "notional": 0,
      "features": {},
      "bar_time": null,
      "open_time": "2026-07-13T06:33:30",
      "closed": false,
      "close_price": null,
      "close_reason": null,
      "result": null,
      "protected_sl": null,
      "runner_active": false,
      "runner_regime": null,
      "bars_since_close": 0,
      "price_triggers": [],
      "watcher_tp": null,
      "watcher_sl": null,
      "manual_tp": null,
      "manual_sl": null,
      "sl_tp_source": null,
      "software_watch_units": 0.0
    },
    "BATS:TSLA": {
      "pair": "BATS:TSLA",
      "direction": "short",
      "entry": 396.1,
      "tp": null,
      "sl": null,
      "atr": 0,
      "size": 1.0,
      "notional": 0,
      "features": {},
      "bar_time": null,
      "open_time": "2026-07-13T06:37:12",
      "closed": false,
      "close_price": null,
      "close_reason": null,
      "result": null,
      "protected_sl": null,
      "runner_active": false,
      "runner_regime": null,
      "bars_since_close": 0,
      "price_triggers": [],
      "watcher_tp": null,
      "watcher_sl": null,
      "manual_tp": null,
      "manual_sl": null,
      "sl_tp_source": null,
      "software_watch_units": 0.0
    },
    "BATS:HPE": {
      "pair": "BATS:HPE",
      "direction": "short",
      "entry": 47.1,
      "tp": null,
      "sl": null,
      "atr": 0,
      "size": 1.0,
      "notional": 0,
      "features": {},
      "bar_time": null,
      "open_time": "2026-07-13T06:41:55",
      "closed": false,
      "close_price": null,
      "close_reason": null,
      "result": null,
      "protected_sl": null,
      "runner_active": false,
      "runner_regime": null,
      "bars_since_close": 0,
      "price_triggers": [],
      "watcher_tp": null,
      "watcher_sl": null,
      "manual_tp": null,
      "manual_sl": null,
      "sl_tp_source": null,
      "software_watch_units": 0.0
    },
    "TVC:DJI": {
      "pair": "TVC:DJI",
      "direction": "long",
      "entry": 52807.27,
      "tp": null,
      "sl": null,
      "atr": 0,
      "size": 1.0,
      "notional": 0,
      "features": {},
      "bar_time": null,
      "open_time": "2026-07-13T06:54:27",
      "closed": false,
      "close_price": null,
      "close_reason": null,
      "result": null,
      "protected_sl": null,
      "runner_active": false,
      "runner_regime": null,
      "bars_since_close": 0,
      "price_triggers": [],
      "watcher_tp": null,
      "watcher_sl": null,
      "manual_tp": null,
      "manual_sl": null,
      "sl_tp_source": null,
      "software_watch_units": 0.0
    },
    "BATS:AMGN": {
      "pair": "BATS:AMGN",
      "direction": "short",
      "entry": 357.0,
      "tp": null,
      "sl": null,
      "atr": 0,
      "size": 1.0,
      "notional": 0,
      "features": {},
      "bar_time": null,
      "open_time": "2026-07-13T07:19:11",
      "closed": false,
      "close_price": null,
      "close_reason": null,
      "result": null,
      "protected_sl": null,
      "runner_active": false,
      "runner_regime": null,
      "bars_since_close": 0,
      "price_triggers": [],
      "watcher_tp": null,
      "watcher_sl": null,
      "manual_tp": null,
      "manual_sl": null,
      "sl_tp_source": null,
      "software_watch_units": 0.0
    },
    "OANDA:GBPUSD": {
      "pair": "OANDA:GBPUSD",
      "direction": "short",
      "entry": 1.33645,
      "tp": null,
      "sl": null,
      "atr": 0,
      "size": 1.0,
      "notional": 0,
      "features": {},
      "bar_time": null,
      "open_time": "2026-07-13T07:16:52",
      "closed": true,
      "close_price": null,
      "close_reason": "synced_from_oanda",
      "result": null,
      "protected_sl": null,
      "runner_active": false,
      "runner_regime": null,
      "bars_since_close": 0,
      "price_triggers": [],
      "watcher_tp": null,
      "watcher_sl": null,
      "manual_tp": null,
      "manual_sl": null,
      "sl_tp_source": null,
      "software_watch_units": 0.0
    },
    "TVC:DXY": {
      "pair": "TVC:DXY",
      "direction": "long",
      "entry": 101.122,
      "tp": null,
      "sl": null,
      "atr": 0,
      "size": 1.0,
      "notional": 0,
      "features": {},
      "bar_time": null,
      "open_time": "2026-07-13T07:17:31",
      "closed": false,
      "close_price": null,
      "close_reason": null,
      "result": null,
      "protected_sl": null,
      "runner_active": false,
      "runner_regime": null,
      "bars_since_close": 0,
      "price_triggers": [],
      "watcher_tp": null,
      "watcher_sl": null,
      "manual_tp": null,
      "manual_sl": null,
      "sl_tp_source": null,
      "software_watch_units": 0.0
    },
    "BATS:MS": {
      "pair": "BATS:MS",
      "direction": "long",
      "entry": 224.32,
      "tp": null,
      "sl": null,
      "atr": 0,
      "size": 1.0,
      "notional": 0,
      "features": {},
      "bar_time": null,
      "open_time": "2026-07-13T07:49:13",
      "closed": false,
      "close_price": null,
      "close_reason": null,
      "result": null,
      "protected_sl": null,
      "runner_active": false,
      "runner_regime": null,
      "bars_since_close": 0,
      "price_triggers": [],
      "watcher_tp": null,
      "watcher_sl": null,
      "manual_tp": null,
      "manual_sl": null,
      "sl_tp_source": null,
      "software_watch_units": 0.0
    },
    "BATS:GS": {
      "pair": "BATS:GS",
      "direction": "long",
      "entry": 1099.0,
      "tp": null,
      "sl": null,
      "atr": 0,
      "size": 1.0,
      "notional": 0,
      "features": {},
      "bar_time": null,
      "open_time": "2026-07-13T09:27:00",
      "closed": false,
      "close_price": null,
      "close_reason": null,
      "result": null,
      "protected_sl": null,
      "runner_active": false,
      "runner_regime": null,
      "bars_since_close": 0,
      "price_triggers": [],
      "watcher_tp": null,
      "watcher_sl": null,
      "manual_tp": null,
      "manual_sl": null,
      "sl_tp_source": null,
      "software_watch_units": 0.0
    },
    "FX:GBPNZD": {
      "pair": "FX:GBPNZD",
      "direction": "short",
      "entry": 2.31592,
      "tp": null,
      "sl": null,
      "atr": 0,
      "size": 1.0,
      "notional": 0,
      "features": {},
      "bar_time": null,
      "open_time": "2026-07-13T09:34:37",
      "closed": false,
      "close_price": null,
      "close_reason": null,
      "result": null,
      "protected_sl": null,
      "runner_active": false,
      "runner_regime": null,
      "bars_since_close": 0,
      "price_triggers": [],
      "watcher_tp": null,
      "watcher_sl": null,
      "manual_tp": null,
      "manual_sl": null,
      "sl_tp_source": null,
      "software_watch_units": 0.0
    },
    "TVC:JP30Y": {
      "pair": "TVC:JP30Y",
      "direction": "short",
      "entry": 3.824,
      "tp": null,
      "sl": null,
      "atr": 0,
      "size": 1.0,
      "notional": 0,
      "features": {},
      "bar_time": null,
      "open_time": "2026-07-13T20:51:15",
      "closed": false,
      "close_price": null,
      "close_reason": null,
      "result": null,
      "protected_sl": null,
      "runner_active": false,
      "runner_regime": null,
      "bars_since_close": 0,
      "price_triggers": [],
      "watcher_tp": null,
      "watcher_sl": null,
      "manual_tp": null,
      "manual_sl": null,
      "sl_tp_source": null,
      "software_watch_units": 0.0
    },
    "OANDA:USDCAD": {
      "pair": "OANDA:USDCAD",
      "direction": "short",
      "entry": 1.40894,
      "tp": 1.39524,
      "sl": 1.41497,
      "atr": 0,
      "size": 10000,
      "notional": 0,
      "features": {},
      "bar_time": null,
      "open_time": "2026-07-14T02:00:40",
      "closed": false,
      "close_price": null,
      "close_reason": null,
      "result": null,
      "protected_sl": null,
      "runner_active": false,
      "runner_regime": null,
      "bars_since_close": 0,
      "price_triggers": [],
      "watcher_tp": null,
      "watcher_sl": null,
      "manual_tp": null,
      "manual_sl": null,
      "sl_tp_source": null,
      "software_watch_units": 0.0
    },
    "TVC:US05Y": {
      "pair": "TVC:US05Y",
      "direction": "short",
      "entry": 4.353,
      "tp": null,
      "sl": null,
      "atr": 0,
      "size": 1.0,
      "notional": 0,
      "features": {},
      "bar_time": null,
      "open_time": "2026-07-14T05:24:42",
      "closed": false,
      "close_price": null,
      "close_reason": null,
      "result": null,
      "protected_sl": null,
      "runner_active": false,
      "runner_regime": null,
      "bars_since_close": 0,
      "price_triggers": [],
      "watcher_tp": null,
      "watcher_sl": null,
      "manual_tp": null,
      "manual_sl": null,
      "sl_tp_source": null,
      "software_watch_units": 0.0
    },
    "OANDA:AUDJPY": {
      "pair": "OANDA:AUDJPY",
      "direction": "long",
      "entry": 112.836,
      "tp": 114.119,
      "sl": 112.253,
      "atr": 0,
      "size": 10000,
      "notional": 0,
      "features": {},
      "bar_time": null,
      "open_time": "2026-07-14T05:30:22",
      "closed": false,
      "close_price": null,
      "close_reason": null,
      "result": null,
      "protected_sl": null,
      "runner_active": false,
      "runner_regime": null,
      "bars_since_close": 0,
      "price_triggers": [],
      "watcher_tp": null,
      "watcher_sl": null,
      "manual_tp": null,
      "manual_sl": null,
      "sl_tp_source": null,
      "software_watch_units": 0.0
    },
    "TVC:US30Y": {
      "pair": "TVC:US30Y",
      "direction": "short",
      "entry": 5.065,
      "tp": null,
      "sl": null,
      "atr": 0,
      "size": 1.0,
      "notional": 0,
      "features": {},
      "bar_time": null,
      "open_time": "2026-07-14T05:30:23",
      "closed": false,
      "close_price": null,
      "close_reason": null,
      "result": null,
      "protected_sl": null,
      "runner_active": false,
      "runner_regime": null,
      "bars_since_close": 0,
      "price_triggers": [],
      "watcher_tp": null,
      "watcher_sl": null,
      "manual_tp": null,
      "manual_sl": null,
      "sl_tp_source": null,
      "software_watch_units": 0.0
    },
    "TVC:US02Y": {
      "pair": "TVC:US02Y",
      "direction": "short",
      "entry": 4.183,
      "tp": null,
      "sl": null,
      "atr": 0,
      "size": 1.0,
      "notional": 0,
      "features": {},
      "bar_time": null,
      "open_time": "2026-07-14T05:30:37",
      "closed": false,
      "close_price": null,
      "close_reason": null,
      "result": null,
      "protected_sl": null,
      "runner_active": false,
      "runner_regime": null,
      "bars_since_close": 0,
      "price_triggers": [],
      "watcher_tp": null,
      "watcher_sl": null,
      "manual_tp": null,
      "manual_sl": null,
      "sl_tp_source": null,
      "software_watch_units": 0.0
    },
    "TVC:US10Y": {
      "pair": "TVC:US10Y",
      "direction": "short",
      "entry": 4.581,
      "tp": null,
      "sl": null,
      "atr": 0,
      "size": 1.0,
      "notional": 0,
      "features": {},
      "bar_time": null,
      "open_time": "2026-07-14T05:30:37",
      "closed": false,
      "close_price": null,
      "close_reason": null,
      "result": null,
      "protected_sl": null,
      "runner_active": false,
      "runner_regime": null,
      "bars_since_close": 0,
      "price_triggers": [],
      "watcher_tp": null,
      "watcher_sl": null,
      "manual_tp": null,
      "manual_sl": null,
      "sl_tp_source": null,
      "software_watch_units": 0.0
    },
    "TVC:US20Y": {
      "pair": "TVC:US20Y",
      "direction": "short",
      "entry": 5.085,
      "tp": null,
      "sl": null,
      "atr": 0,
      "size": 1.0,
      "notional": 0,
      "features": {},
      "bar_time": null,
      "open_time": "2026-07-14T05:30:46",
      "closed": false,
      "close_price": null,
      "close_reason": null,
      "result": null,
      "protected_sl": null,
      "runner_active": false,
      "runner_regime": null,
      "bars_since_close": 0,
      "price_triggers": [],
      "watcher_tp": null,
      "watcher_sl": null,
      "manual_tp": null,
      "manual_sl": null,
      "sl_tp_source": null,
      "software_watch_units": 0.0
    },
    "BATS:MSTR": {
      "pair": "BATS:MSTR",
      "direction": "long",
      "entry": 94.77,
      "tp": null,
      "sl": null,
      "atr": 0,
      "size": 1.0,
      "notional": 0,
      "features": {},
      "bar_time": null,
      "open_time": "2026-07-14T06:30:14",
      "closed": false,
      "close_price": null,
      "close_reason": null,
      "result": null,
      "protected_sl": null,
      "runner_active": false,
      "runner_regime": null,
      "bars_since_close": 0,
      "price_triggers": [],
      "watcher_tp": null,
      "watcher_sl": null,
      "manual_tp": null,
      "manual_sl": null,
      "sl_tp_source": null,
      "software_watch_units": 0.0
    },
    "BATS:CAT": {
      "pair": "BATS:CAT",
      "direction": "short",
      "entry": 945.0,
      "tp": null,
      "sl": null,
      "atr": 0,
      "size": 1.0,
      "notional": 0,
      "features": {},
      "bar_time": null,
      "open_time": "2026-07-14T06:56:15",
      "closed": false,
      "close_price": null,
      "close_reason": null,
      "result": null,
      "protected_sl": null,
      "runner_active": false,
      "runner_regime": null,
      "bars_since_close": 0,
      "price_triggers": [],
      "watcher_tp": null,
      "watcher_sl": null,
      "manual_tp": null,
      "manual_sl": null,
      "sl_tp_source": null,
      "software_watch_units": 0.0
    },
    "BATS:UNH": {
      "pair": "BATS:UNH",
      "direction": "short",
      "entry": 422.98,
      "tp": null,
      "sl": null,
      "atr": 0,
      "size": 1.0,
      "notional": 0,
      "features": {},
      "bar_time": null,
      "open_time": "2026-07-14T07:45:33",
      "closed": false,
      "close_price": null,
      "close_reason": null,
      "result": null,
      "protected_sl": null,
      "runner_active": false,
      "runner_regime": null,
      "bars_since_close": 0,
      "price_triggers": [],
      "watcher_tp": null,
      "watcher_sl": null,
      "manual_tp": null,
      "manual_sl": null,
      "sl_tp_source": null,
      "software_watch_units": 0.0
    },
    "BATS:MRK": {
      "pair": "BATS:MRK",
      "direction": "short",
      "entry": 120.68,
      "tp": null,
      "sl": null,
      "atr": 0,
      "size": 1.0,
      "notional": 0,
      "features": {},
      "bar_time": null,
      "open_time": "2026-07-14T07:59:50",
      "closed": false,
      "close_price": null,
      "close_reason": null,
      "result": null,
      "protected_sl": null,
      "runner_active": false,
      "runner_regime": null,
      "bars_since_close": 0,
      "price_triggers": [],
      "watcher_tp": null,
      "watcher_sl": null,
      "manual_tp": null,
      "manual_sl": null,
      "sl_tp_source": null,
      "software_watch_units": 0.0
    },
    "HYPERLIQUID:RENDERUSDC.P": {
      "pair": "HYPERLIQUID:RENDERUSDC.P",
      "direction": "long",
      "entry": 1.52442,
      "tp": 1.7087,
      "sl": 1.4682,
      "atr": 0,
      "size": 10000,
      "notional": 0,
      "features": {},
      "bar_time": null,
      "open_time": "2026-07-15T16:27:52",
      "closed": false,
      "close_price": null,
      "close_reason": null,
      "result": null,
      "protected_sl": null,
      "runner_active": false,
      "runner_regime": null,
      "bars_since_close": 0,
      "price_triggers": [],
      "watcher_tp": 1.7087,
      "watcher_sl": 1.4682,
      "manual_tp": null,
      "manual_sl": null,
      "sl_tp_source": null,
      "software_watch_units": 0.0
    },
    "HYPERLIQUID:SOLUSDC.P": {
      "pair": "HYPERLIQUID:SOLUSDC.P",
      "direction": "long",
      "entry": 77.357,
      "tp": 86.76,
      "sl": 73.86,
      "atr": 0,
      "size": 10000,
      "notional": 0,
      "features": {},
      "bar_time": null,
      "open_time": "2026-07-15T16:41:13",
      "closed": false,
      "close_price": null,
      "close_reason": null,
      "result": null,
      "protected_sl": null,
      "runner_active": false,
      "runner_regime": null,
      "bars_since_close": 0,
      "price_triggers": [],
      "watcher_tp": 86.76,
      "watcher_sl": 73.86,
      "manual_tp": null,
      "manual_sl": null,
      "sl_tp_source": null,
      "software_watch_units": 0.0
    }
  }
}